{
  "project_info": {
    "project_number": "124910059912",
    "project_id": "aavas-1ad68",
    "storage_bucket": "aavas-1ad68.appspot.com"
  },
  "client": [
    {
      "client_info": {
        "mobilesdk_app_id": "1:124910059912:android:24e729fb9e13751931fa3d",
        "android_client_info": {
          "package_name": "com.example.shop_app"
        }
      },
      "oauth_client": [
        {
          "client_id": "124910059912-m484chhtd9c27525ftbq7i94eh1qp7qg.apps.googleusercontent.com",
          "client_type": 3
        }
      ],
      "api_key": [
        {
          "current_key": "AIzaSyBmSC8oikMwJrFiwtr-TtrM1NSwYGYm-RM"
        }
      ],
      "services": {
        "appinvite_service": {
          "other_platform_oauth_client": [
            {
              "client_id": "124910059912-m484chhtd9c27525ftbq7i94eh1qp7qg.apps.googleusercontent.com",
              "client_type": 3
            }
          ]
        }
      }
    }
  ],
  "configuration_version": "1"
}